maht.py
mahtlib-0.2.0.dist-info/licenses/LICENSE
mahtlib-0.2.0.dist-info/METADATA
mahtlib-0.2.0.dist-info/WHEEL
mahtlib-0.2.0.dist-info/top_level.txt
mahtlib-0.2.0.dist-info/RECORD
