Metadata-Version: 2.4
Name: mahtlib
Version: 0.2.0
Summary: Минимальная библиотека для работы с OpenAI API. Просто maht('ваш вопрос')
Author-email: Danial <your-email@example.com>
License: MIT
Project-URL: Homepage, https://github.com/yourusername/maht
Project-URL: Repository, https://github.com/yourusername/maht
Keywords: openai,gpt,chatgpt,ai,api,minimal
Classifier: Development Status :: 4 - Beta
Classifier: Intended Audience :: Developers
Classifier: License :: OSI Approved :: MIT License
Classifier: Programming Language :: Python :: 3
Classifier: Programming Language :: Python :: 3.7
Classifier: Programming Language :: Python :: 3.8
Classifier: Programming Language :: Python :: 3.9
Classifier: Programming Language :: Python :: 3.10
Classifier: Programming Language :: Python :: 3.11
Classifier: Programming Language :: Python :: 3.12
Classifier: Topic :: Software Development :: Libraries :: Python Modules
Requires-Python: >=3.7
License-File: LICENSE
Dynamic: license-file
